paddlefsl/__init__.py
paddlefsl/backbones/__init__.py
paddlefsl/backbones/conv.py
paddlefsl/backbones/gin.py
paddlefsl/backbones/mlp.py
paddlefsl/backbones/plm.py
paddlefsl/backbones/rc_init_vector.py
paddlefsl/backbones/rc_position_embedding.py
paddlefsl/backbones/relationnet.py
paddlefsl/datasets/__init__.py
paddlefsl/datasets/cifar_fs.py
paddlefsl/datasets/cub_fs.py
paddlefsl/datasets/cv_dataset.py
paddlefsl/datasets/fc100.py
paddlefsl/datasets/few_rel.py
paddlefsl/datasets/mini_imagenet.py
paddlefsl/datasets/mol_dataset.py
paddlefsl/datasets/nlp_dataset.py
paddlefsl/datasets/omniglot.py
paddlefsl/datasets/tiered.py
paddlefsl/datasets/tiered_imagenet.py
paddlefsl/model_zoo/__init__.py
paddlefsl/model_zoo/anil.py
paddlefsl/model_zoo/maml.py
paddlefsl/model_zoo/maml_mol.py
paddlefsl/model_zoo/par.py
paddlefsl/model_zoo/pet.py
paddlefsl/model_zoo/protonet.py
paddlefsl/model_zoo/ptuning.py
paddlefsl/model_zoo/relationnet.py
paddlefsl/model_zoo/siamese.py
paddlefsl/task_sampler/__init__.py
paddlefsl/task_sampler/taskset.py
paddlefsl/utils/__init__.py
paddlefsl/utils/clone_model.py
paddlefsl/utils/count_model_params.py
paddlefsl/utils/eval.py
paddlefsl/utils/io.py
paddlefsl/utils/manual_gradient_descent.py
paddlefsl-1.1.0.dist-info/LICENSE
paddlefsl-1.1.0.dist-info/METADATA
paddlefsl-1.1.0.dist-info/WHEEL
paddlefsl-1.1.0.dist-info/top_level.txt
paddlefsl-1.1.0.dist-info/RECORD
