Metadata-Version: 2.1
Name: paddlefsl
Version: 1.1.0
Summary: PaddleFSL is a Python library for few-shot learning
Home-page: https://github.com/tata1661/FSL-Mate/tree/master/PaddleFSL
Author: PaddleFSL authors
Author-email: wangyaqing01@baidu.com
License: Apache 2.0
Keywords: few-shot-learning,one-shot-learning,meta-learning,paddlepaddle,deep-learning
Platform: UNKNOWN
Classifier: Programming Language :: Python :: 3
Classifier: Programming Language :: Python :: 3.6
Classifier: Programming Language :: Python :: 3.7
Classifier: Programming Language :: Python :: 3.8
Classifier: License :: OSI Approved :: Apache Software License
Classifier: Operating System :: OS Independent
Requires-Python: >=3.6
